myanmartools/__init__.py
myanmartools/_params.py
myanmartools/zawgyi_detector.py
myanmartools/resources/__init__.py
myanmartools/resources/compatibility.tsv
myanmartools/resources/zawgyiUnicodeModel.dat
myanmartools-1.2.1.dist-info/LICENSE
myanmartools-1.2.1.dist-info/METADATA
myanmartools-1.2.1.dist-info/WHEEL
myanmartools-1.2.1.dist-info/top_level.txt
myanmartools-1.2.1.dist-info/RECORD
