Metadata-Version: 2.1
Name: myanmartools
Version: 1.2.1
Summary: Tools for processing font encodings used in Myanmar
Home-page: https://github.com/google/myanmar-tools
Author: William (Wai Yan) Zhu
Author-email: williamzhu345@gmail.com
License: Apache License, Version 2.0
Keywords: burmese,encoding,myanmar,nlp,unicode,zawgyi
Platform: any
Classifier: Development Status :: 4 - Beta
Classifier: Intended Audience :: Developers
Classifier: Intended Audience :: Science/Research
Classifier: License :: OSI Approved :: Apache Software License
Classifier: Operating System :: OS Independent
Classifier: Programming Language :: Python :: 3.8
Classifier: Topic :: Text Processing
Requires-Python: >=3.8
